starfiles/__init__.py
starfiles-1.0.5.dist-info/LICENSE
starfiles-1.0.5.dist-info/METADATA
starfiles-1.0.5.dist-info/WHEEL
starfiles-1.0.5.dist-info/top_level.txt
starfiles-1.0.5.dist-info/RECORD
