Metadata-Version: 2.1
Name: starfiles
Version: 1.0.5
Summary: Simplify starfiles, if it was not simple already.
Home-page: https://github.com/dwiftejb/starfiles
Author: DwifteJB
Author-email: dwifte@icloud.com
License: MIT
Platform: UNKNOWN
Classifier: Programming Language :: Python :: 3
Classifier: Programming Language :: Python :: 3.4
Classifier: Programming Language :: Python :: 3.8
Requires-Dist: requests
